datadrawer/VERSION.txt
datadrawer/__init__.py
datadrawer/src/__init__.py
datadrawer/src/draw.py
datadrawer/src/stat.py
datadrawer/utils/__init__.py
tests/__init__.py
tests/test_stat.py
datadrawer-1.0.0.dist-info/METADATA
datadrawer-1.0.0.dist-info/WHEEL
datadrawer-1.0.0.dist-info/top_level.txt
datadrawer-1.0.0.dist-info/RECORD
